mtmtoolkit/__init__.py
mtmtoolkit/__main__.py
mtmtoolkit/webserv.py
mtmtoolkit-0.0.9a0.dist-info/METADATA
mtmtoolkit-0.0.9a0.dist-info/WHEEL
mtmtoolkit-0.0.9a0.dist-info/entry_points.txt
mtmtoolkit-0.0.9a0.dist-info/top_level.txt
mtmtoolkit-0.0.9a0.dist-info/RECORD
