Metadata-Version: 2.1
Name: mtmtoolkit
Version: 0.0.9a0
Summary: A convenient tool for chemists or researchers who need to prepare Gaussian input files quickly, without manually converting SMILES to XYZ format or typing out the Gaussian input file parameters by hand. 
Home-page: https://github.com/rrau-bsu/MTMToolkit
Author: rrau-bsu
Author-email: ryanrau@u.boisestate.edu
License: MIT
Platform: UNKNOWN
Requires-Dist: PyQt6
Requires-Dist: PyQt6-WebEngine
Requires-Dist: rdkit
Requires-Dist: flask
